formate/__init__.py
formate/__main__.py
formate/classes.py
formate/config.py
formate/dynamic_quotes.py
formate/ellipses.py
formate/exceptions.py
formate/imports.py
formate/mini_hooks.py
formate/py.typed
formate/reformat_generics.py
formate/utils.py
formate-1.1.2.dist-info/LICENSE
formate-1.1.2.dist-info/METADATA
formate-1.1.2.dist-info/WHEEL
formate-1.1.2.dist-info/entry_points.txt
formate-1.1.2.dist-info/RECORD
