Metadata-Version: 2.2
Name: formate
Version: 1.1.2
Summary: Python formatting mate.
Author-email: Dominic Davis-Foster <dominic@davis-foster.co.uk>
License: MIT
Keywords: formatting,linting
Home-page: https://github.com/python-formate/formate
Project-URL: Issue Tracker, https://github.com/python-formate/formate/issues
Project-URL: Source Code, https://github.com/python-formate/formate
Project-URL: Documentation, https://formate.readthedocs.io/en/latest
Platform: Windows
Platform: macOS
Platform: Linux
Classifier: Development Status :: 4 - Beta
Classifier: Environment :: Console
Classifier: Intended Audience :: Developers
Classifier: License :: OSI Approved :: MIT License
Classifier: Operating System :: OS Independent
Classifier: Programming Language :: Python
Classifier: Programming Language :: Python :: 3 :: Only
Classifier: Programming Language :: Python :: 3.7
Classifier: Programming Language :: Python :: 3.8
Classifier: Programming Language :: Python :: 3.9
Classifier: Programming Language :: Python :: 3.10
Classifier: Programming Language :: Python :: 3.11
Classifier: Programming Language :: Python :: 3.12
Classifier: Programming Language :: Python :: 3.13
Classifier: Programming Language :: Python :: Implementation :: CPython
Classifier: Programming Language :: Python :: Implementation :: PyPy
Classifier: Typing :: Typed
Requires-Python: >=3.7
Requires-Dist: astatine>=0.3.1
Requires-Dist: asttokens>=2.0.4
Requires-Dist: attr-utils>=0.5.5
Requires-Dist: attrs>=20.3.0
Requires-Dist: click>=7.1.2
Requires-Dist: consolekit>=1.0.0
Requires-Dist: dom-toml>=2.2.0
Requires-Dist: domdf-python-tools>=2.5.0
Requires-Dist: isort>=5.5.2
Requires-Dist: prettyprinter>=0.18.0
Requires-Dist: tokenize-rt>=5.0.0
Requires-Dist: typing-extensions>=3.7.4.3
Requires-Dist: yapf<0.43.0,>=0.30.0
